{
  "trigger": true,
  "modules": [
    "verification-link"
  ],
  "parentResource": "reactAmplifyCognito",
  "functionName": "reactAmplifyCognitoCustomMessage",
  "resourceName": "reactAmplifyCognitoCustomMessage",
  "parentStack": "auth",
  "triggerEnvs": [
    {
      "key": "RESOURCENAME",
      "value": "resourceName"
    }
  ],
  "triggerDir": "/usr/lib/node_modules/@aws-amplify/cli/node_modules/amplify-category-auth/provider-utils/awscloudformation/triggers/CustomMessage",
  "triggerTemplate": "CustomMessage.json.ejs",
  "triggerEventPath": "CustomMessage.event.json",
  "roleName": "reactAmplifyCognitoCustomMessage",
  "skipEdit": true,
  "REDIRECTURL": "",
  "EMAILSUBJECT": "Account confirmation",
  "EMAILMESSAGE": "Hi",
  "RESOURCENAME": "resourceName",
  "enableCors": false
}